faktory_prometheus_exporter.py
faktory_prometheus_exporter-0.2.0.dist-info/LICENSE
faktory_prometheus_exporter-0.2.0.dist-info/METADATA
faktory_prometheus_exporter-0.2.0.dist-info/WHEEL
faktory_prometheus_exporter-0.2.0.dist-info/entry_points.txt
faktory_prometheus_exporter-0.2.0.dist-info/top_level.txt
faktory_prometheus_exporter-0.2.0.dist-info/RECORD
