Metadata-Version: 2.1
Name: faktory-prometheus-exporter
Version: 0.2.0
Summary: Faktory metrics exporter for Prometheus, written in Python
Author-email: Matthieu Rigal <matthieu.rigal@a2ei.org>
License: MIT License
Project-URL: Repository, https://github.com/prospect-server/faktory-prometheus-exporter
Project-URL: PyPI, https://pypi.org/project/faktory-prometheus-exporter/
Project-URL: Gitlab Mirror, https://gitlab.com/prospect-energy/faktory-prometheus-exporter
Keywords: faktory,prometheus,metrics
Classifier: Development Status :: 4 - Beta
Classifier: Environment :: Console
Classifier: Intended Audience :: Developers
Classifier: Operating System :: OS Independent
Classifier: License :: OSI Approved :: MIT License
Classifier: Programming Language :: Python
Classifier: Programming Language :: Python :: 3.8
Classifier: Programming Language :: Python :: 3.9
Classifier: Programming Language :: Python :: 3.10
Classifier: Programming Language :: Python :: 3.11
Classifier: Programming Language :: Python :: 3.12
Classifier: Programming Language :: Python :: 3 :: Only
Classifier: Topic :: System :: Monitoring
Classifier: Topic :: Software Development :: Libraries
Requires-Python: >=3.8
License-File: LICENSE
Requires-Dist: click <9
Requires-Dist: prometheus-client <1
Requires-Dist: pyfaktory <1
Provides-Extra: dev
Requires-Dist: pre-commit <4 ; extra == 'dev'
Requires-Dist: ruff <1 ; extra == 'dev'
